tasty_agent/__init__.py
tasty_agent/_version.py
tasty_agent/server.py
tasty_agent-3.2.0.dist-info/METADATA
tasty_agent-3.2.0.dist-info/WHEEL
tasty_agent-3.2.0.dist-info/entry_points.txt
tasty_agent-3.2.0.dist-info/licenses/LICENSE
tasty_agent-3.2.0.dist-info/RECORD
