Metadata-Version: 2.4
Name: tasty-agent
Version: 3.2.0
Summary: A Model Context Protocol server for interacting with TastyTrade brokerage accounts
Author-email: Ferdous <ferdous@hey.com>
License-File: LICENSE
Keywords: broker,mcp,model context protocol,robinhood,tastytrade,trading,wallstreetbets
Classifier: Intended Audience :: End Users/Desktop
Classifier: Intended Audience :: Financial and Insurance Industry
Classifier: License :: OSI Approved :: MIT License
Classifier: Programming Language :: Python :: 3.12
Classifier: Topic :: Office/Business :: Financial
Requires-Python: >=3.12
Requires-Dist: aiocache>=0.12.2
Requires-Dist: aiolimiter==1.2.1
Requires-Dist: humanize>=4.12.3
Requires-Dist: mcp[cli]>=v1.14.0
Requires-Dist: tabulate>=0.9.0
Requires-Dist: tastytrade>=11.0.0
